[{"CrawlerDate":20200720,"NumFavorite":8,"NumShare":1,"author":"KerrisdaleCap","content":"$I: @NewAmerica hosted an informative panel discussion featuring $I &amp; $SESG reps and other involved parties to disc\u2026 https:\/\/t.co\/KUcznRiXZq","pubdate":"20180702132712"},{"CrawlerDate":20200720,"NumFavorite":20,"NumShare":2,"author":"ActivistShorts","content":"From $12.34 to $4.35 in less than one year. Now without a CEO, MiMedx is heading for bankruptcy says @AlderLaneeggs. https:\/\/t.co\/0C63qSjQkV","pubdate":"20180702145236"}]